struct_lmm/__init__.py
struct_lmm/_lmm.py
struct_lmm/_testit.py
struct_lmm/test/__init__.py
struct_lmm/test/test_structlmm.py
struct_lmm-0.3.2.dist-info/LICENSE.md
struct_lmm-0.3.2.dist-info/METADATA
struct_lmm-0.3.2.dist-info/WHEEL
struct_lmm-0.3.2.dist-info/top_level.txt
struct_lmm-0.3.2.dist-info/zip-safe
struct_lmm-0.3.2.dist-info/RECORD
