Metadata-Version: 2.1
Name: struct-lmm
Version: 0.3.2
Summary: Linear mixed model to study multivariate genotype-environment interactions
Home-page: https://github.com/limix/struct-lmm
Author: D. Horta, P. Casale, R. Moore
Author-email: rm18@sanger.ac.uk
Maintainer: Danilo Horta
Maintainer-email: horta@ebi.ac.uk
License: MIT
Download-URL: https://github.com/limix/struct-lmm
Keywords: lmm,gwas,environment
Platform: Windows
Platform: MacOS
Platform: Linux
Classifier: Development Status :: 5 - Production/Stable
Classifier: License :: OSI Approved :: MIT License
Classifier: Operating System :: OS Independent
Classifier: Programming Language :: Python
Requires-Dist: chiscore (>=0.2.2)
Requires-Dist: glimix-core (>=3.1.11)
Requires-Dist: numpy-sugar (>=1.5.1)
Requires-Dist: numpy (>=1.17)
Requires-Dist: pytest-doctestplus (>=0.8.0)
Requires-Dist: pytest (>=5)
